{"u9dffl59dUL6xaloQl7MtQ==":"chirp_white-01-1-122x122.png","H0UHb6nXTCT2L8UbBjGVXQ==":"web_images-3-1710x1692.png","7e3vM6AQzWq4xEUK0RzNtQ==":"web_images-03-3-1482x980.png","R+aPwVwZn6wCARfRkj4mBA==":"web_images-1-1482x1000.png","BaCzEIIn8ds4tygLUaJ+pg==":"chirp_marigold-140x138.png","FO53z+5LkUW3Zz4NxfdOuA==":"web_images-1-1772x1196.png","bwgC9j7YvIaOGP/5VMhcBg==":"chirp_marigold-1-122x122.jpg","2ZkNfVUGAXwJ1St0Wio6zg==":"chirp_marigold-122x121.png","D2sprnvGBiiX3q3wZW9ZaA==":"chirp_pink-1-158x158.png","mxJUVzAeyOz1kW4POrjDyw==":"logoandiddesign-02-2-1160x1160.jpg","JqZIJgwY8B+XYBn7+jecIg==":"logoandidentity-2-1160x774.png","Ml6Vb9qsFqW/kHB4vOkHCQ==":"logoandidentity-02-2-1286x1286.png","Na3a/rDwdzI7x4XPK2Pwfw==":"logoandidentity-02-02-2-1382x1700.png","PfQ1wshXCV4+b4bDSrHanw==":"logoandidentity-02-02-02_again-2-1252x875.png","e8EyFC1Ozi1Y10orXUAdWQ==":"logo_examples_afrs-2000x1378.jpg","3Yu/4ZMVEjp3X8zFNpzunw==":"logo_examples_afrs_square-2000x2000.jpg","bCTWnV7TmzWTsSZ3QgeuMQ==":"logo_examples_afrs-2000x1333.jpg","B+PczeRJ4RbtINL4EzdNPQ==":"business%20card_ovenly_port-1-1112x638.png","BccZgg3pdZeavLnNvLmhWA==":"logo_examples_ovenly-957x638.jpg","u44fsMxvm59DYbMpdjbNqw==":"logo_examples_commonthread-2000x1333.jpg","5yZxQJZOC2etwe1ecMO3Pw==":"logo_examples_puppyphat-984x656.jpg","A6KeJYbG9NUVlvV4X2VC9A==":"logo_examples_puppyphat-2000x1333.jpg","4rX4o2DFTUOwBChke+tvPw==":"logo_examples_afrs-1-2000x1333.jpg","u/3c0tn1hD7A3EFhXZgEKw==":"logo_examples_katehunter-2000x1333.jpg","Mm6nT0SLqG7Ms3mfS1XHdg==":"logo_examples_afrs-2-2000x1333.jpg","Pu0nU+QcRn+YrubB3353Dg==":"logo_examples_ellehairdressing-2000x1333.jpg","OGsfU2rgnBCmJZeWTJrpAw==":"logo_examples_ellehairdressing2-2000x1333.jpg","QBb+cD2OzH2ZSm9WhaYtOg==":"logo_examples_tangled-2000x1333.jpg","6MgPfKvrY8HRU+Ta0yozbA==":"logo_examples_ovenly2-2000x1333.jpg","t2HBMMdGvPji8FdU0u9z1w==":"logo_examples_digico-2000x1334.jpg","szqHPgk+3j/gE8S3/Cn7mw==":"logo_examples_moses-2000x1333.jpg","UAc7kepzJPkrSn4uqTRvmw==":"background4.jpg","CkxM58NXomGfEQM5Z6f5JA==":"print_design-3-1382x921.png","JCczs2DQRN1kbFbTZUlNgA==":"print_design-03-3-1382x1074.png","mbFkYX5grIXnb8F3Hx0E6Q==":"print_design-03-3-1382x1036.png","cz6I5qWDkFgiizDj3eIhXQ==":"logo_examples_katehunter-676x451.jpg","hvXk7tikI4e17XIp3Fuvsg==":"print_examples_abiscan-2000x1333.jpg","6HhtbxKO8b5NNGk7nxovTw==":"ovenly_business%20card%20mockup-2000x1455.jpg","oLatu0nR9rt1Gx3Ni5hyRg==":"glass%20jar%20mockup-2000x1333.jpg","WAiiZBaFacsChyWiIMZMGg==":"glass%20jar%20mockup-2000x1333.jpg","phBndjx76Xv6hoBolUsPyw==":"glass%20jar%20mockup-2000x1333.jpg","zkCX2U2NmNgUryEoynEQCw==":"glass%20jar%20mockup-2000x1333.jpg","G9jWMPAPILqoQpeoVCQjqQ==":"icons-6-473x473.png","WSZpAm0EV08Ss937mC0GLQ==":"icons-7-473x473.png","DRhDLGr7ntItLG3ZMM+ktA==":"icons-8-473x473.png","KKqzW04jwBKaTm3rP2zFFg==":"icons-9-474x473.png","98JAVRIz3fX2spnmB9wIsA==":"icons-9-473x473.png","uoTOX3rKWLQYt1qnFfDdUw==":"icons-10-473x473.png","o1qYzYgjf4caVfdhW0VWCg==":"icons-10-474x473.png","VKcMjPF0oYGvMtH7uP07Qg==":"t2t_icons-1-625x417.jpg","g4PtY+w9ViIacagU4NnXrg==":"mbr-1920x1275.jpg","m2zisFvcDFOWoVf0vJgWww==":"print_examples_giveahoot-2000x1333.jpg","bsQfw/xokATWQk5na5LxYg==":"four_sections-1-1776x1184.png","sSN43RqXuiC89HYjvwgIjA==":"chirp_studio-1-1776x1184.png","taG1vuT+2MdcFiNydc08pQ==":"print_design_examples_mcu2_brochure-2000x1333.jpg","uVdhgWW56uCe1ORwtlS4wQ==":"print_design_examples_mcu2_brochure-2000x1334.jpg","KMcihiORQzAguaK7uOaRAg==":"print_examples_ovenly-2000x1333.jpg","lSUGpnO0HfGVID8nV6IjrA==":"print_examples_bua-1953x1302.jpg","pAg+hdmMu+ev04SBpVOf0Q==":"print_examples_tablet%20to%20tablet-2000x1333.jpg","oWQNamT5CPNk1242yyA4rQ==":"print_examples_tablet%20to%20tablet-2000x1333.jpg","RMzFYF/3jTTKAfkj5P+0Mg==":"chirp_blue-208x208.png","ZYZASTNs7abhz7X+SlQhYA==":"chirp_light_blue-208x208.png","xRWMTVPR1okscvAuvoq/nQ==":"print_design_metal%20boxes%20mockup-2000x1333.jpg","/EUFttqVS5ViUMEfhoNqWQ==":"print_design_metal%20boxes-2000x1333.jpg","E6DWaAKh7kCrs/fjREdjQQ==":"print_design_metal%20boxes-2000x1333.jpg","hoA1wl+iypaZ7bQ+AhfMEw==":"four_sections-4-1382x921.png","Lglcqco4cew3YWws2YPDUA==":"digitalwebdesign-4-1382x921.png","dPP6yJxv3GM3sIUFE05Osg==":"digitalwebdesign-04-4-1382x1060.png","r/YPo0wOmZDE5zVyrViWwg==":"jld_icons_all-1-2000x1332.png","8LAVANgQxKu1Its6NMsSgA==":"jld_icons_all-01-1-2000x1332.png","pkqoLPt2oMNHQmzoUKY8Wg==":"hiking_icons_all-2000x1414.png","x7recxc0UY/QumxyEcetww==":"hiking_icons_all-1-2000x1334.png","Ju9lnFXhn99v21s5QbeFVQ==":"ovenly-13-2000x1333.jpg","tFPyzRiFrbfMo73bemBjqQ==":"lightbulb%20image-2000x1333.jpg","OTtSYnh/Z5ROqmd90mfCxA==":"web_examples_jld1-2000x1333.jpg","E5Q8jCDF+LxYT9E/Gam3Bg==":"jld_icons_all-2-2000x1332.png","eXFoak1Ueufn+D8HDdFhhg==":"jld_icons_all-01-2-2000x1332.png","VgLNVUF+ohPYbCPZaoy2NA==":"web_example_jld2-2000x1333.jpg","Iz7KM/H107H0fH/090FGLw==":"print_design-03-03-3-1382x1382.png","sCongwhTnh9e1OOr4TGnOA==":"print_design-03-03-03-3-1382x1279.png","3E+xgvA7wD5jTtsiFpvEdg==":"logoandiddesign-02-2-1382x1382.jpg","r3eXor7VIqgYRgkte4fmPw==":"logoandidentity-2-1382x1212.png","VTKhIS5asQ58asqSK2zmyQ==":"web_images_tangled-2000x1333.jpg","lIOVuBb0h4tpASJ9GScO+g==":"web_examples_sandstorm-1881x1254.jpg","8XhMwn4uPnPBOPCTFaYlTg==":"illustration-5-1382x921.png","8h7DE8LXWRj5Hz1j+eHIwg==":"illustration-05-5-1382x921.png","LaT06iWUUkFA4mFyYLDSnw==":"natalia_family-photo-2000x1333.jpg","Rw40fEoKMJe97ljY5IhmMg==":"blue_prints_layflat-2000x1333.jpg","AB79ZhHSM9UDdSbNgbTOpQ==":"bargate_selfie-2000x1333.jpg","gBqRpsTeWfPEH1u+2YqmSg==":"found%20myself-2000x1334.jpg","p9t1ECfqHG/loDrD6qUDzA==":"prints_various-1345x896.jpg","NA68fcoP2R6RFRlgQPgi0A==":"bench_square_herecomes-2000x1334.jpg","fXcpuem4tkhNvCvt0vyRSA==":"paris_photo-2000x1333.jpg","6wIjTfj6b9tfUrqUrgq4fQ==":"blades_of_glory-brighter-photo_sage-2000x1333.jpg","YnWx5xT8Z2S6NiVc8O1OBg==":"blades_of_glory-sage-photo-2000x1333.jpg","J0bbK8BRYEjBwiAxdeQ6RQ==":"for_love_not_money_cantaloupe-photo-2000x1333.jpg","MWp8B9Q7Z3jFlU16WDiYiA==":"ikea_image-1-2000x1334.jpg","oPNhYjQ45FNejKa0qUicOA==":"prints_packaged-2000x1333.jpg","lHOmhiKVCV0ZU33oT2sZOg==":"blackwhite_promo-2000x1333.jpg","17uHnsTVP0OLWwK42KMXQQ==":"ikea_image-01-1-2000x1334.jpg","RmVGicva0EyJNVrcx2l7Hg==":"star_icon-10-240x240.png","vDe1oGZPRsT3acSXKycFuQ==":"star_icon-10-10-240x240.png","YWWrilYdj48Mq6bzb9hAhw==":"star_icon-10-10-676x676.png","37QIOLVQXzaeJawdgw8rNw==":"star_icon-10-10-560x560.png","3uogOrqHYAyS0DryidgSPQ==":"star_backgrnd-10-560x560.png","OtbnB4WDS4guinhYiV+zmQ==":"star_backgrnd-10-10-946x946.png","TdWMc7yNsZFwb8Dgb8EoXA==":"illustration_example_magazine-2000x1333.jpg","1SIRriLa7W0DDMA4zK08xA==":"illustration_example_magazine-1-2000x1333.jpg","WnsieqTAqYVGkWgKysZZtw==":"illustration-05-5-1382x996.png","UnH8UtfmmJVFz1811jOLEQ==":"illustration-05-5-1382x1089.png","na9kfgfTevsxjkrDZAiBQw==":"illustration-05-6-1382x1089.png"}